splunk_handler_zuul/__init__.py
splunk_handler_zuul-0.1.0.dist-info/LICENSE
splunk_handler_zuul-0.1.0.dist-info/METADATA
splunk_handler_zuul-0.1.0.dist-info/WHEEL
splunk_handler_zuul-0.1.0.dist-info/top_level.txt
splunk_handler_zuul-0.1.0.dist-info/RECORD
