Metadata-Version: 2.1
Name: splunk-handler-zuul
Version: 0.1.0
Summary: A Python logging handler that sends zuul conponent logs to Splunk
Home-page: https://github.com/lidall/splunk_handler
Author: Lida Liu
Author-email: lindaliu0712@gmail.com
License: MIT License
Platform: UNKNOWN
Classifier: Development Status :: 4 - Beta
Classifier: Intended Audience :: Developers
Classifier: License :: OSI Approved :: MIT License
Classifier: Natural Language :: English
Classifier: Operating System :: POSIX :: Linux
Classifier: Operating System :: MacOS :: MacOS X
Classifier: Programming Language :: Python
Classifier: Programming Language :: Python :: 2.7
Classifier: Programming Language :: Python :: 3.4
Classifier: Programming Language :: Python :: 3.5
Classifier: Programming Language :: Python :: 3.6
Classifier: Programming Language :: Python :: 3.7
Classifier: Programming Language :: Python :: 3.8
Classifier: Topic :: System :: Logging
Requires-Dist: requests (<3.0.0,>=2.6.0)
Requires-Dist: python-json-logger (>=2.0.1)
